pythonbook20210303/__init__.py
pythonbook20210303-1.0.0.dist-info/LICENSE.txt
pythonbook20210303-1.0.0.dist-info/METADATA
pythonbook20210303-1.0.0.dist-info/WHEEL
pythonbook20210303-1.0.0.dist-info/top_level.txt
pythonbook20210303-1.0.0.dist-info/RECORD
